attrim/__init__.py
attrim/apps.py
attrim/filters.py
attrim/trans_str.py
attrim/admin/__init__.py
attrim/admin/cls/__init__.py
attrim/admin/cls/main.py
attrim/admin/cls/views/__init__.py
attrim/admin/cls/views/delete.py
attrim/admin/cls/views/edit.py
attrim/admin/cls/views/list.py
attrim/admin/product/__init__.py
attrim/admin/product/forms.py
attrim/migrations/0001_initial.py
attrim/migrations/__init__.py
attrim/models/__init__.py
attrim/models/attribute.py
attrim/models/cls.py
attrim/models/option.py
attrim/models/type.py
attrim/restapi/__init__.py
attrim/restapi/api_populator.py
attrim/restapi/views.py
attrim/restapi/serializers/__init__.py
attrim/restapi/serializers/cls.py
attrim/restapi/serializers/fields.py
attrim/restapi/serializers/option.py
attrim/restapi/serializers/product_type.py
attrim/static/attrim/admin/dist/app.js
attrim/static/attrim/admin/dist/polyfills.js
attrim/static/attrim/admin/dist/vendor.css
attrim/static/attrim/admin/dist/vendor.js
attrim/static/attrim/admin/dist/assets/flags.png
attrim/static/attrim/admin/dist/assets/icons.eot
attrim/static/attrim/admin/dist/assets/icons.svg
attrim/static/attrim/admin/dist/assets/icons.ttf
attrim/static/attrim/admin/dist/assets/icons.woff
attrim/static/attrim/admin/dist/assets/icons.woff2
attrim/templates/attrim/admin/cls/edit.jinja
attrim/templates/attrim/admin/product/attrim.jinja
attrim/tests/__init__.py
attrim/tests/test_filters.py
attrim/tests/test_generators.py
attrim/tests/test_integration.py
attrim/tests/admin/__init__.py
attrim/tests/admin/test_cls.py
attrim/tests/admin/test_product.py
attrim/tests/models/__init__.py
attrim/tests/models/test_attributes.py
attrim/tests/models/test_cls.py
attrim/tests/models/test_options.py
attrim/tests/models/test_type.py
attrim/tests/restapi/__init__.py
attrim/tests/restapi/test_cls.py
attrim/tests/restapi/test_options.py
attrim/tests/restapi/test_product_type.py
attrim/tests/testproject/__init__.py
shuup_attrim-0.13.1.5.dist-info/DESCRIPTION.rst
shuup_attrim-0.13.1.5.dist-info/METADATA
shuup_attrim-0.13.1.5.dist-info/RECORD
shuup_attrim-0.13.1.5.dist-info/WHEEL
shuup_attrim-0.13.1.5.dist-info/entry_points.txt
shuup_attrim-0.13.1.5.dist-info/metadata.json
shuup_attrim-0.13.1.5.dist-info/top_level.txt
