Metadata-Version: 2.0
Name: shuup-attrim
Version: 0.13.1.5
Summary: Multi-value product attributes addon for Shuup E-Commerce Platform
Home-page: https://gitlab.com/nilit/shuup-attrim
Author: UNKNOWN
Author-email: UNKNOWN
License: MIT
Keywords: shuup,attributes
Platform: UNKNOWN
Classifier: Development Status :: 3 - Alpha
Classifier: Framework :: Django :: 1.9
Classifier: Intended Audience :: Developers
Classifier: License :: OSI Approved :: MIT License
Classifier: Topic :: Software Development
Classifier: Programming Language :: Python :: 3.5
Classifier: Topic :: Software Development :: Libraries :: Python Modules
Classifier: Topic :: Internet :: WWW/HTTP
Classifier: Topic :: Office/Business
Requires-Dist: shuup (==2.0)
Requires-Dist: psycopg2 (<3,>=2.6.2)
Requires-Dist: shuup-testutils (<0.13,>=0.12)
Requires-Dist: shuup-utils (<0.8,>=0.7)
